setup.cfg
setup.py
flask_filters/__init__.py
flask_filters/filters.py
flask_filters.egg-info/PKG-INFO
flask_filters.egg-info/SOURCES.txt
flask_filters.egg-info/dependency_links.txt
flask_filters.egg-info/not-zip-safe
flask_filters.egg-info/requires.txt
flask_filters.egg-info/top_level.txt