Metadata-Version: 1.0
Name: flask-filters
Version: 0.3
Summary: The Flask Filter to use with flask-restful and Relational DB
Home-page: https://gitlab.com/yogeshkamble/flask-filters
Author: Yogesh Kamble
Author-email: yogesh.kamble102@gmail.com
License: MIT
Platform: UNKNOWN
